<?xml version="1.0" encoding="UTF-8"?>
<odoo>
    <data>
        <record model='ir.ui.view' id='tms_toll_data_tree'>
            <field name='name'>tms_toll_data.tree</field>
            <field name='model'>tms.toll.data</field>
            <field name='arch' type='xml'>
                <tree string='Toll Data'>
                    <field name="name"/>
                    <field name="num_tag"/>
                    <field name="economic_number"/>
                    <field name="date"/>
                    <field name="import_rate"/>
                </tree>
            </field>
        </record>
        <record id='action_toll_data' model='ir.actions.act_window'>
            <field name='name'>Iave toll data</field>
            <field name='res_model'>tms.toll.data</field>
            <field name='view_type'>form</field>
            <field name='view_mode'>tree,form</field>
        </record>
        <menuitem id="menu_tms_settings_toll_data" name="Iave information" parent="tms.menu_tms_settings" sequence="50"/>
        <menuitem action="action_toll_data" id="tms_iave" parent="menu_tms_settings_toll_data" sequence="15"/>
    </data>
</odoo>
