<?xml version="1.0" encoding="UTF-8"?>
<odoo>
    <data>
        <record model='ir.ui.view' id='tms_base_form'>
            <field name='name'>TMS Base Form View</field>
            <field name='model'>tms.base</field>
            <field name='arch' type='xml'>
                <form>
                    <sheet>
                        <h1>
                            <field name='name' placeholder='Base name'/>
                        </h1>
                        <group>
                            <group string='Sequences'>
                                <field name='travel_sequence_id'/>
                                <field name='expense_sequence_id'/>
                                <field name='waybill_sequence_id'/>
                                <field name='advance_sequence_id'/>
                                <field name='fuel_log_sequence_id'/>
                            </group>
                            <group string="Journals">
                                <field name='advance_journal_id'/>
                                <field name='fuelvoucher_journal_id'/>
                                <field name='expense_journal_id'/>
                                <field name='supplier_journal_id'/>
                                <field name='waybill_journal_id'/>
                            </group>
                            <group string='Accounts'>
                                <field name='account_fuel_id'/>
                                <field name='account_advance_id'/>
                                <field name='account_freight_id'/>
                                <field name='account_moves_id'/>
                                <field name='account_highway_tolls_id'/>
                                <field name='account_insurance_id'/>
                                <field name='account_other_id'/>
                            </group>
                            <group string='Products'>
                                <field name='fuelvoucher_product_id'/>
                                <field name='advance_product_id'/>
                                <field name='waybill_freight_id'/>
                                <field name='waybill_moves_id'/>
                                <field name='waybill_highway_tolls_id'/>
                                <field name='waybill_insurance_id'/>
                                <field name='waybill_other_product_id'/>
                                <field name="ieps_product_id"/>
                            </group>
                        </group>
                    </sheet>
                </form>
            </field>
        </record>
        <record model='ir.ui.view' id='tms_base_tree'>
            <field name='name'>TMS Base Tree View</field>
            <field name='model'>tms.base</field>
            <field name='arch' type='xml'>
                <tree string='TMS Base'>
                    <field name='name'/>
                </tree>
            </field>
        </record>
        <record id='action_tms_base' model='ir.actions.act_window'>
            <field name='name'>TMS Base Action</field>
            <field name='res_model'>tms.base</field>
            <field name='view_type'>form</field>
            <field name='view_mode'>tree,form</field>
        </record>
        <menuitem
            id="tms_base_menu"
            name="Base"
            parent="tms.menu_tms_settings"
            action="action_tms_base"
            sequence="99"/>
    </data>
</odoo>